html2django/__init__.py
html2django/djangohtml.py
html2django-1.0.dist-info/LICENSE.txt
html2django-1.0.dist-info/METADATA
html2django-1.0.dist-info/WHEEL
html2django-1.0.dist-info/entry_points.txt
html2django-1.0.dist-info/top_level.txt
html2django-1.0.dist-info/RECORD
