Metadata-Version: 2.1
Name: html2django
Version: 1.0
Summary: A Python script to modify HTML files for Django templates
Home-page: https://github.com/haxsysgit/html2django
Author: Elenasulu Arinze
Author-email: pentacker@gmail.com
Classifier: Development Status :: 3 - Alpha
Classifier: License :: OSI Approved :: MIT License
Classifier: Operating System :: OS Independent
Classifier: Programming Language :: Python :: 3
Classifier: Programming Language :: Python :: 3.7
Classifier: Programming Language :: Python :: 3.8
Classifier: Programming Language :: Python :: 3.9
Requires-Python: >=3.7
License-File: LICENSE.txt
Requires-Dist: beautifulsoup4
